lark/Auth.py
lark/Records.py
lark/__init__.py
test/__init__.py
utils/ErrorUtils.py
utils/RestfulUtils.py
utils/__init__.py
vo/__init__.py
vo/lark/LarkAuthTenantAccessTokenResponse.py
vo/lark/LarkBaseResponse.py
vo/lark/LarkBitableRecordItem.py
vo/lark/LarkBitableRecordsResponse.py
vo/lark/__init__.py
lark_bitable_sdk-0.0.0.3.dist-info/METADATA
lark_bitable_sdk-0.0.0.3.dist-info/WHEEL
lark_bitable_sdk-0.0.0.3.dist-info/top_level.txt
lark_bitable_sdk-0.0.0.3.dist-info/RECORD
