Metadata-Version: 2.1
Name: lark-bitable-sdk
Version: 0.0.0.3
Summary: A python-made lark bitable sdk.
Home-page: UNKNOWN
Author: Tianhao Zhang
Author-email: genji9071@gmail.com
License: MIT
Project-URL: Source, https://github.com/genji9071/lark-bitable-sdk
Project-URL: Tracker, https://github.com/genji9071/lark-bitable-sdk/issues
Keywords: lark bitable
Platform: UNKNOWN
Requires-Python: >=3
Requires-Dist: pydantic (==1.8.2)
Requires-Dist: requests (==2.28.1)
